ddnet_mcpserver/__init__.py
ddnet_mcpserver/__main__.py
ddnet_mcpserver/server.py
ddnet_mcpserver/tools/__init__.py
ddnet_mcpserver/tools/ddnetprocess.py
ddnet_mcpserver-0.1.2.dist-info/METADATA
ddnet_mcpserver-0.1.2.dist-info/WHEEL
ddnet_mcpserver-0.1.2.dist-info/entry_points.txt
ddnet_mcpserver-0.1.2.dist-info/licenses/LICENSE
ddnet_mcpserver-0.1.2.dist-info/RECORD
