Metadata-Version: 2.4
Name: ddnet-mcpserver
Version: 0.1.2
Summary: 基于FastMCP的MCP服务器，提供简单的计算和问候功能
Project-URL: Homepage, https://github.com/silverhi/ddnet-mcpserver
Project-URL: Bug Tracker, https://github.com/silverhi/ddnet-mcpserver/issues
Author-email: silverhi <molei8686138@gmail.com>
License: MIT
License-File: LICENSE
Classifier: License :: OSI Approved :: MIT License
Classifier: Operating System :: OS Independent
Classifier: Programming Language :: Python :: 3
Requires-Python: >=3.12
Requires-Dist: fastmcp>=2.2.3
Requires-Dist: mcp>=1.6.0
Requires-Dist: psutil>=7.0.0
